bienabee_qtbot/__init__.py
bienabee_qtbot/qtest/__init__.py
bienabee_qtbot/qtest/api_qtest.py
bienabee_qtbot/qtest/custom_field.py
bienabee_qtbot/qtest/module.py
bienabee_qtbot/qtest/project.py
bienabee_qtbot/qtest/sso_user.py
bienabee_qtbot/qtest/test_case.py
bienabee_qtbot/qtest/test_case_fields.py
bienabee_qtbot/qtest/test_cycle.py
bienabee_qtbot/qtest/test_suite.py
bienabee_qtbot/qtest/user.py
bienabee_qtbot/utilities/__init__.py
bienabee_qtbot/utilities/data_utils.py
bienabee_qtbot/utilities/error_handling.py
bienabee_qtbot-0.1.0.dist-info/LICENSE
bienabee_qtbot-0.1.0.dist-info/METADATA
bienabee_qtbot-0.1.0.dist-info/WHEEL
bienabee_qtbot-0.1.0.dist-info/top_level.txt
bienabee_qtbot-0.1.0.dist-info/RECORD
