Metadata-Version: 2.1
Name: bienabee-qtbot
Version: 0.1.0
Summary: This is the Bienabee Technologies Tricentis qTest API wrapper and utility kit
Home-page: https://bienabee.com/
Author: LouieT
Author-email: info@bienabee.com
Project-URL: Bug Tracker, https://gitlab.com/bienabee/qtest-utilities/bienabee-qtbot/-/issues
Classifier: Development Status :: 2 - Pre-Alpha
Classifier: Intended Audience :: Developers
Classifier: Programming Language :: Python :: 3
Classifier: License :: OSI Approved :: Apache Software License
Classifier: Operating System :: OS Independent
Requires-Python: >=3.7
License-File: LICENSE
Requires-Dist: requests
Requires-Dist: python-dateutil (==2.8.2)
